pythondata_cpu_mor1kx/__init__.py
pythondata_cpu_mor1kx/verilog/.gitignore
pythondata_cpu_mor1kx/verilog/Jenkinsfile
pythondata_cpu_mor1kx/verilog/LICENSE
pythondata_cpu_mor1kx/verilog/README.md
pythondata_cpu_mor1kx/verilog/mor1kx.core
pythondata_cpu_mor1kx/verilog/.github/workflows/Dockerfile
pythondata_cpu_mor1kx/verilog/.github/workflows/ci.yml
pythondata_cpu_mor1kx/verilog/bench/formal/.gitignore
pythondata_cpu_mor1kx/verilog/bench/formal/Makefile
pythondata_cpu_mor1kx/verilog/bench/formal/f_multiclock_op.v
pythondata_cpu_mor1kx/verilog/bench/formal/fspr_master.v
pythondata_cpu_mor1kx/verilog/bench/formal/fspr_slave.v
pythondata_cpu_mor1kx/verilog/bench/formal/fwb_master.v
pythondata_cpu_mor1kx/verilog/bench/formal/mor1kx.gtkw
pythondata_cpu_mor1kx/verilog/bench/formal/mor1kx.sby
pythondata_cpu_mor1kx/verilog/bench/formal/mor1kx_bus_if_wb32.sby
pythondata_cpu_mor1kx/verilog/bench/formal/mor1kx_cache_lru.sby
pythondata_cpu_mor1kx/verilog/bench/formal/mor1kx_cpu_cappuccino.gtkw
pythondata_cpu_mor1kx/verilog/bench/formal/mor1kx_cpu_cappuccino.sby
pythondata_cpu_mor1kx/verilog/bench/formal/mor1kx_ctrl_cappuccino.sby
pythondata_cpu_mor1kx/verilog/bench/formal/mor1kx_dcache.gtkw
pythondata_cpu_mor1kx/verilog/bench/formal/mor1kx_dcache.sby
pythondata_cpu_mor1kx/verilog/bench/formal/mor1kx_decode.sby
pythondata_cpu_mor1kx/verilog/bench/formal/mor1kx_decode_execute_cappuccino.sby
pythondata_cpu_mor1kx/verilog/bench/formal/mor1kx_dmmu.gtkw
pythondata_cpu_mor1kx/verilog/bench/formal/mor1kx_dmmu.sby
pythondata_cpu_mor1kx/verilog/bench/formal/mor1kx_execute_alu.sby
pythondata_cpu_mor1kx/verilog/bench/formal/mor1kx_execute_ctrl_cappuccino.sby
pythondata_cpu_mor1kx/verilog/bench/formal/mor1kx_fetch_cappuccino.sby
pythondata_cpu_mor1kx/verilog/bench/formal/mor1kx_icache.sby
pythondata_cpu_mor1kx/verilog/bench/formal/mor1kx_immu.sby
pythondata_cpu_mor1kx/verilog/bench/formal/mor1kx_lsu_cappuccino.gtkw
pythondata_cpu_mor1kx/verilog/bench/formal/mor1kx_lsu_cappuccino.sby
pythondata_cpu_mor1kx-5.2.post151.dist-info/LICENSE
pythondata_cpu_mor1kx-5.2.post151.dist-info/METADATA
pythondata_cpu_mor1kx-5.2.post151.dist-info/WHEEL
pythondata_cpu_mor1kx-5.2.post151.dist-info/top_level.txt
pythondata_cpu_mor1kx-5.2.post151.dist-info/RECORD
