Metadata-Version: 2.2
Name: pythondata-cpu-mor1kx
Version: 5.2.post151
Summary: Python module containing verilog files for OpenRISC1000 cpu.
Home-page: https://github.com/litex-hub/pythondata-cpu-mor1kx
Author: LiteX Authors
Author-email: litex@googlegroups.com
Project-URL: Bug Tracker, https://github.com/litex-hub/pythondata-cpu-mor1kx/issues
Project-URL: Source Code, https://github.com/litex-hub/pythondata-cpu-mor1kx
Classifier: Programming Language :: Python :: 3
Classifier: License :: OSI Approved :: Mozilla Public License 2.0 (MPL 2.0)
Classifier: Operating System :: OS Independent
Requires-Python: >=3.5
License-File: LICENSE
Dynamic: author
Dynamic: author-email
Dynamic: classifier
Dynamic: description
Dynamic: description-content-type
Dynamic: home-page
Dynamic: project-url
Dynamic: requires-python
Dynamic: summary
